{
  "home-page-title": "CheckReel - Check Before You Post",
  "home-hero-title": "CheckReel",
  "home-hero-subtitle": "Don't guess  check before you post.",
  "home-benefit-1": " Pre-check any video, image or audio",
  "home-benefit-2": " Instant AI-powered compliance report",
  "home-benefit-3": " Your privacy is fully protected",
  "home-subscribe-button": "Subscribe Now",
  "home-subscription-note": "$4.99/month after trial period",
  "home-active-users": " 2,729 active users",
  "home-platforms-title": "Supported Platforms",
  "home-about-title": "About CheckReel",
  "home-about-content": "CheckReel is part of Alwafer Media, specialising in social-media management, AI apps, and precision marketing.",
  "dashboard-upload-title": "Upload Content to Check",
  "dashboard-upload-text": "Drag and drop your file here or click to browse",
  "dashboard-platform-title": "Select Target Platform",
  "dashboard-scan-btn": "Start Content Check",
  "dashboard-results-title": "Compliance Report",
  "dashboard-score-label": "Compliance Score",
  "dashboard-issues-title": "Issues Found",
  "dashboard-recommendations-title": "Recommendations",
  "dashboard-upgrade-title": "Upgrade Your Plan",
  "dashboard-upgrade-message": "You've reached your scan limit. Upgrade to continue checking your content."
}
